twikit/__init__.py
twikit/client.py
twikit/errors.py
twikit/http.py
twikit/message.py
twikit/trend.py
twikit/tweet.py
twikit/user.py
twikit/utils.py
twikit/twikit_async/__init__.py
twikit/twikit_async/client.py
twikit/twikit_async/errors.py
twikit/twikit_async/http.py
twikit/twikit_async/message.py
twikit/twikit_async/trend.py
twikit/twikit_async/tweet.py
twikit/twikit_async/user.py
twikit/twikit_async/utils.py
twikit_pro-1.1.3.dist-info/LICENSE
twikit_pro-1.1.3.dist-info/METADATA
twikit_pro-1.1.3.dist-info/WHEEL
twikit_pro-1.1.3.dist-info/top_level.txt
twikit_pro-1.1.3.dist-info/RECORD
