Metadata-Version: 2.1
Name: twikit_pro
Version: 1.1.3
Summary: Twitter API wrapper for python with **no API key required**.
Home-page: https://github.com/yanjlee/twikit
Author: yanjlee
Author-email: yanjlee@163.com
License: MIT
License-File: LICENSE
Requires-Dist: httpx
